LICENSE
MANIFEST.in
README.md
setup.py
bool_to_int8_ray/__init__.py
bool_to_int8_ray/serialize.py
bool_to_int8_ray.egg-info/PKG-INFO
bool_to_int8_ray.egg-info/SOURCES.txt
bool_to_int8_ray.egg-info/dependency_links.txt
bool_to_int8_ray.egg-info/requires.txt
bool_to_int8_ray.egg-info/top_level.txt
bool_to_int8_ray.egg-info/zip-safe
test/__init__.py
test/speedtest.py
test/test_serialize.py