Metadata-Version: 2.1
Name: bool-to-int8-ray
Version: 0.2.0
Summary: bool to int8 serialization with ray.io
Home-page: http://github.com/ulf1/bool-to-int8-ray
Author: Ulf Hamster
Author-email: 554c46@gmail.com
License: Apache License 2.0
Platform: UNKNOWN
Requires-Python: >=3.7
License-File: LICENSE
